{
  "adminLogin": [],
  "loggedin": [],
  "admin": [
    {
      "username": "ronin",
      "password": "admin123",
      "id": 1
    }
  ],
  "members": [
    {
      "AccountName": "Jann",
      "passwordUser": "5555",
      "AccountNum": "65656",
      "Balance": "2.312312312312332e+37",
      "id": 1
    },
    {
      "AccountName": "Maria Elena Josefa Manso",
      "passwordUser": "2323",
      "AccountNum": "9374733",
      "Balance": "201978",
      "id": 2
    },
    {
      "AccountName": "hellzzzo",
      "passwordUser": "1212",
      "AccountNum": "993733",
      "Balance": "105474468",
      "id": 3
    },
    {
      "AccountName": "ronin",
      "passwordUser": "6666",
      "AccountNum": "1222212",
      "Balance": "117278",
      "id": 4
    },
    {
      "AccountName": "JANE",
      "passwordUser": "0567",
      "AccountNum": "36930567",
      "Balance": "2333",
      "id": 5
    },
    {
      "AccountName": "Red",
      "passwordUser": "4789",
      "AccountNum": "19674789",
      "Balance": "22199",
      "id": 6
    },
    {
      "AccountName": "jimbing",
      "passwordUser": "3536",
      "AccountNum": "90413536",
      "Balance": "199999",
      "id": 7
    },
    {
      "AccountName": "gg",
      "passwordUser": "7576",
      "AccountNum": "91017576",
      "Balance": "12222",
      "id": 8
    },
    {
      "AccountName": "sddad",
      "passwordUser": "6475",
      "AccountNum": "97766475",
      "Balance": "1222222",
      "id": 9
    },
    {
      "AccountName": "lola",
      "passwordUser": "4567",
      "AccountNum": "60452030",
      "Balance": "173242",
      "id": 10
    },
    {
      "AccountName": "John Silva",
      "passwordUser": "3910",
      "AccountNum": "87123139",
      "Balance": "100000000",
      "id": 11
    },
    {
      "AccountName": "Crankie",
      "passwordUser": "1234",
      "AccountNum": "34083397",
      "Balance": "128933",
      "id": 12
    }
  ],
  "records": [
    {
      "record_type": "Withdraw",
      "record_date": "1 / 7/ 2023",
      "record_time": "1 : 18 : 3",
      "record_amount": "2688",
      "record_balance": "105486267",
      "recordId": 3,
      "id": 1
    },
    {
      "record_type": "Withdraw",
      "record_date": "1 / 7/ 2023",
      "record_time": "1 : 18 : 6",
      "record_amount": "1000",
      "record_balance": "105485267",
      "recordId": 3,
      "id": 2
    },
    {
      "record_type": "Withdraw",
      "record_date": "1 / 7/ 2023",
      "record_time": "1 : 18 : 8",
      "record_amount": "2222",
      "record_balance": "105483045",
      "recordId": 3,
      "id": 3
    },
    {
      "record_type": "Withdraw",
      "record_date": "1 / 7/ 2023",
      "record_time": "1 : 18 : 13",
      "record_amount": "400",
      "record_balance": "105482645",
      "recordId": 3,
      "id": 4
    },
    {
      "record_type": "Withdraw",
      "record_date": "1 / 7/ 2023",
      "record_time": "1 : 19 : 44",
      "record_amount": "2444",
      "record_balance": "105480201",
      "recordId": 3,
      "id": 5
    },
    {
      "record_type": "Withdraw",
      "record_date": "1 / 7/ 2023",
      "record_time": "1 : 19 : 48",
      "record_amount": "1000",
      "record_balance": "105479201",
      "recordId": 3,
      "id": 6
    },
    {
      "record_type": "Withdraw",
      "record_date": "1 / 7/ 2023",
      "record_time": "1 : 19 : 53",
      "record_amount": "2333",
      "record_balance": "105476868",
      "recordId": 3,
      "id": 7
    },
    {
      "record_type": "Withdraw",
      "record_date": "1 / 7/ 2023",
      "record_time": "1 : 23 : 44",
      "record_amount": "1000",
      "record_balance": "105475868",
      "recordId": 3,
      "id": 8
    },
    {
      "record_type": "Withdraw",
      "record_date": "1 / 7/ 2023",
      "record_time": "14 : 34 : 13",
      "record_amount": "10000",
      "record_balance": "655413",
      "recordId": 2,
      "id": 9
    },
    {
      "record_type": "Withdraw",
      "record_date": "1 / 7/ 2023",
      "record_time": "14 : 34 : 39",
      "record_amount": "333",
      "record_balance": "655080",
      "recordId": 2,
      "id": 10
    },
    {
      "record_type": "Withdraw",
      "record_date": "1 / 7/ 2023",
      "record_time": "14 : 34 : 41",
      "record_amount": "153",
      "record_balance": "654927",
      "recordId": 2,
      "id": 11
    },
    {
      "record_type": "Withdraw",
      "record_date": "1 / 7/ 2023",
      "record_time": "14 : 34 : 44",
      "record_amount": "1000",
      "record_balance": "653927",
      "recordId": 2,
      "id": 12
    },
    {
      "record_type": "Withdraw",
      "record_date": "1 / 7/ 2023",
      "record_time": "14 : 52 : 13",
      "record_amount": "10000",
      "record_balance": "643927",
      "recordId": 2,
      "id": 13
    },
    {
      "record_type": "Withdraw",
      "record_date": "1 / 7/ 2023",
      "record_time": "14 : 56 : 0",
      "record_amount": "1222",
      "record_balance": "642705",
      "recordId": 2,
      "id": 14
    },
    {
      "record_type": "Withdraw",
      "record_date": "1 / 7/ 2023",
      "record_time": "15 : 0 : 36",
      "record_amount": "642005",
      "record_balance": "0",
      "recordId": 2,
      "id": 15
    },
    {
      "record_type": "Withdraw",
      "record_date": "1 / 7/ 2023",
      "record_time": "16 : 32 : 34",
      "record_amount": "12111",
      "record_balance": "99000",
      "recordId": 2,
      "id": 16
    },
    {
      "record_type": "Withdraw",
      "record_date": "1 / 7/ 2023",
      "record_time": "16 : 32 : 54",
      "record_amount": "12111",
      "record_balance": "86889",
      "recordId": 2,
      "id": 17
    },
    {
      "record_type": "Withdraw",
      "record_date": "1 / 7/ 2023",
      "record_time": "16 : 33 : 53",
      "record_amount": "1211",
      "record_balance": "85678",
      "recordId": 2,
      "id": 18
    },
    {
      "record_type": "Withdraw",
      "record_date": "1 / 7/ 2023",
      "record_time": "16 : 34 : 4",
      "record_amount": "1211",
      "record_balance": "84467",
      "recordId": 2,
      "id": 19
    },
    {
      "record_type": "Withdraw",
      "record_date": "1 / 7/ 2023",
      "record_time": "16 : 38 : 43",
      "record_amount": "12111",
      "record_balance": "72356",
      "recordId": 2,
      "id": 20
    },
    {
      "record_type": "Withdraw",
      "record_date": "1 / 7/ 2023",
      "record_time": "16 : 38 : 52",
      "record_amount": "3333",
      "record_balance": "69023",
      "recordId": 2,
      "id": 21
    },
    {
      "record_type": "Deposit",
      "record_date": "1 / 7/ 2023",
      "record_time": "17 : 6 : 45",
      "record_amount": "12111",
      "record_balance": "84467",
      "recordId": 2,
      "id": 22
    },
    {
      "record_type": "Deposit",
      "record_date": "1 / 7/ 2023",
      "record_time": "17 : 7 : 2",
      "record_amount": "122111",
      "record_balance": "206578",
      "recordId": 2,
      "id": 23
    },
    {
      "record_type": "Withdraw",
      "record_date": "1 / 7/ 2023",
      "record_time": "17 : 9 : 0",
      "record_amount": "700",
      "record_balance": "205878",
      "recordId": 2,
      "id": 24
    },
    {
      "record_type": "Withdraw",
      "record_date": "1 / 7/ 2023",
      "record_time": "17 : 9 : 11",
      "record_amount": "500",
      "record_balance": "205378",
      "recordId": 2,
      "id": 25
    },
    {
      "record_type": "Withdraw",
      "record_date": "1 / 7/ 2023",
      "record_time": "17 : 9 : 22",
      "record_amount": "700",
      "record_balance": "204678",
      "recordId": 2,
      "id": 26
    },
    {
      "record_type": "Withdraw",
      "record_date": "1 / 7/ 2023",
      "record_time": "17 : 9 : 25",
      "record_amount": "800",
      "record_balance": "203878",
      "recordId": 2,
      "id": 27
    },
    {
      "record_type": "Withdraw",
      "record_date": "1 / 7/ 2023",
      "record_time": "17 : 9 : 28",
      "record_amount": "1000",
      "record_balance": "202878",
      "recordId": 2,
      "id": 28
    },
    {
      "record_type": "Withdraw",
      "record_date": "1 / 7/ 2023",
      "record_time": "17 : 9 : 29",
      "record_amount": "900",
      "record_balance": "201978",
      "recordId": 2,
      "id": 29
    },
    {
      "record_type": "Withdraw",
      "record_date": "1 / 7/ 2023",
      "record_time": "21 : 5 : 27",
      "record_amount": "1000",
      "record_balance": "114600",
      "recordId": 4,
      "id": 30
    },
    {
      "record_type": "Withdraw",
      "record_date": "1 / 7/ 2023",
      "record_time": "21 : 5 : 45",
      "record_amount": "2322",
      "record_balance": "112278",
      "recordId": 4,
      "id": 31
    },
    {
      "record_type": "Deposit",
      "record_date": "1 / 7/ 2023",
      "record_time": "21 : 12 : 48",
      "record_amount": "5000",
      "record_balance": "117278",
      "recordId": 4,
      "id": 32
    },
    {
      "record_type": "Deposit",
      "record_date": "1 / 8/ 2023",
      "record_time": "14 : 49 : 3",
      "record_amount": "1250",
      "record_balance": "3750",
      "recordId": 10,
      "id": 33
    },
    {
      "record_type": "Withdraw",
      "record_date": "1 / 8/ 2023",
      "record_time": "14 : 49 : 14",
      "record_amount": "800",
      "record_balance": "2950",
      "recordId": 10,
      "id": 34
    },
    {
      "record_type": "Withdraw",
      "record_date": "1 / 8/ 2023",
      "record_time": "14 : 50 : 18",
      "record_amount": "800",
      "record_balance": "1350",
      "recordId": 10,
      "id": 35
    },
    {
      "record_type": "Withdraw",
      "record_date": "1 / 8/ 2023",
      "record_time": "14 : 50 : 28",
      "record_amount": "1000",
      "record_balance": "350",
      "recordId": 10,
      "id": 36
    },
    {
      "record_type": "Deposit",
      "record_date": "1 / 8/ 2023",
      "record_time": "14 : 51 : 9",
      "record_amount": "180000",
      "record_balance": "180350",
      "recordId": 10,
      "id": 37
    },
    {
      "record_type": "Withdraw",
      "record_date": "1 / 8/ 2023",
      "record_time": "14 : 51 : 13",
      "record_amount": "1000",
      "record_balance": "179350",
      "recordId": 10,
      "id": 38
    },
    {
      "record_type": "Withdraw",
      "record_date": "1 / 8/ 2023",
      "record_time": "14 : 51 : 31",
      "record_amount": "800",
      "record_balance": "178550",
      "recordId": 10,
      "id": 39
    },
    {
      "record_type": "Withdraw",
      "record_date": "1 / 8/ 2023",
      "record_time": "14 : 54 : 40",
      "record_amount": "12",
      "record_balance": "178538",
      "recordId": 10,
      "id": 40
    },
    {
      "record_type": "Withdraw",
      "record_date": "1 / 8/ 2023",
      "record_time": "15 : 0 : 49",
      "record_amount": "12",
      "record_balance": "178526",
      "recordId": 10,
      "id": 41
    },
    {
      "record_type": "Withdraw",
      "record_date": "1 / 8/ 2023",
      "record_time": "15 : 18 : 45",
      "record_amount": "12",
      "record_balance": "178514",
      "recordId": 10,
      "id": 42
    },
    {
      "record_type": "Withdraw",
      "record_date": "1 / 8/ 2023",
      "record_time": "15 : 26 : 16",
      "record_amount": "12",
      "record_balance": "178502",
      "recordId": 10,
      "id": 43
    },
    {
      "record_type": "Withdraw",
      "record_date": "1 / 8/ 2023",
      "record_time": "15 : 26 : 34",
      "record_amount": "12",
      "record_balance": "178490",
      "recordId": 10,
      "id": 44
    },
    {
      "record_type": "Withdraw",
      "record_date": "1 / 8/ 2023",
      "record_time": "15 : 29 : 39",
      "record_amount": "12",
      "record_balance": "178466",
      "recordId": 10,
      "id": 45
    },
    {
      "record_type": "Withdraw",
      "record_date": "1 / 8/ 2023",
      "record_time": "15 : 29 : 43",
      "record_amount": "12",
      "record_balance": "178454",
      "recordId": 10,
      "id": 46
    },
    {
      "record_type": "Withdraw",
      "record_date": "1 / 8/ 2023",
      "record_time": "15 : 38 : 26",
      "record_amount": "12",
      "record_balance": "178442",
      "recordId": 10,
      "id": 47
    },
    {
      "record_type": "Withdraw",
      "record_date": "1 / 8/ 2023",
      "record_time": "15 : 47 : 57",
      "record_amount": "1000",
      "record_balance": "177442",
      "recordId": 10,
      "id": 48
    },
    {
      "record_type": "Withdraw",
      "record_date": "1 / 8/ 2023",
      "record_time": "15 : 50 : 49",
      "record_amount": "500",
      "record_balance": "176942",
      "recordId": 10,
      "id": 49
    },
    {
      "record_type": "Withdraw",
      "record_date": "1 / 8/ 2023",
      "record_time": "15 : 51 : 5",
      "record_amount": "1000",
      "record_balance": "175942",
      "recordId": 10,
      "id": 50
    },
    {
      "record_type": "Withdraw",
      "record_date": "1 / 8/ 2023",
      "record_time": "15 : 51 : 40",
      "record_amount": "1000",
      "record_balance": "174942",
      "recordId": 10,
      "id": 51
    },
    {
      "record_type": "Withdraw",
      "record_date": "1 / 8/ 2023",
      "record_time": "15 : 51 : 51",
      "record_amount": "800",
      "record_balance": "174142",
      "recordId": 10,
      "id": 52
    },
    {
      "record_type": "Withdraw",
      "record_date": "1 / 8/ 2023",
      "record_time": "15 : 53 : 52",
      "record_amount": "200",
      "record_balance": "173942",
      "recordId": 10,
      "id": 53
    },
    {
      "record_type": "Withdraw",
      "record_date": "1 / 8/ 2023",
      "record_time": "15 : 54 : 3",
      "record_amount": "700",
      "record_balance": "173242",
      "recordId": 10,
      "id": 54
    },
    {
      "record_type": "Withdraw",
      "record_date": "1 / 8/ 2023",
      "record_time": "16 : 1 : 35",
      "record_amount": "1000",
      "record_balance": "49000",
      "recordId": 6,
      "id": 55
    },
    {
      "record_type": "Withdraw",
      "record_date": "1 / 8/ 2023",
      "record_time": "16 : 2 : 10",
      "record_amount": "1000",
      "record_balance": "NaN",
      "recordId": 6,
      "id": 56
    },
    {
      "record_type": "Withdraw",
      "record_date": "1 / 8/ 2023",
      "record_time": "16 : 2 : 12",
      "record_amount": "900",
      "record_balance": "NaN",
      "recordId": 6,
      "id": 57
    },
    {
      "record_type": "Withdraw",
      "record_date": "1 / 8/ 2023",
      "record_time": "16 : 2 : 15",
      "record_amount": "800",
      "record_balance": "NaN",
      "recordId": 6,
      "id": 58
    },
    {
      "record_type": "Withdraw",
      "record_date": "1 / 8/ 2023",
      "record_time": "16 : 2 : 17",
      "record_amount": "700",
      "record_balance": "NaN",
      "recordId": 6,
      "id": 59
    },
    {
      "record_type": "Withdraw",
      "record_date": "1 / 8/ 2023",
      "record_time": "16 : 2 : 19",
      "record_amount": "500",
      "record_balance": "NaN",
      "recordId": 6,
      "id": 60
    },
    {
      "record_type": "Deposit",
      "record_date": "1 / 8/ 2023",
      "record_time": "16 : 2 : 53",
      "record_amount": "100000",
      "record_balance": "NaN",
      "recordId": 6,
      "id": 61
    },
    {
      "record_type": "Withdraw",
      "record_date": "1 / 8/ 2023",
      "record_time": "16 : 3 : 15",
      "record_amount": "800",
      "record_balance": "9200",
      "recordId": 6,
      "id": 62
    },
    {
      "record_type": "Deposit",
      "record_date": "1 / 8/ 2023",
      "record_time": "16 : 5 : 41",
      "record_amount": "12999",
      "record_balance": "22199",
      "recordId": 6,
      "id": 63
    },
    {
      "record_type": "Withdraw",
      "record_date": "1 / 8/ 2023",
      "record_time": "22 : 14 : 26",
      "record_amount": "1000",
      "record_balance": "10381",
      "recordId": 1,
      "id": 64
    },
    {
      "record_type": "Deposit",
      "record_date": "1 / 8/ 2023",
      "record_time": "22 : 15 : 16",
      "record_amount": "1000",
      "record_balance": "11381",
      "recordId": 1,
      "id": 65
    },
    {
      "record_type": "Withdraw",
      "record_date": "1 / 8/ 2023",
      "record_time": "22 : 15 : 49",
      "record_amount": "2000",
      "record_balance": "9381",
      "recordId": 1,
      "id": 66
    },
    {
      "record_type": "Withdraw",
      "record_date": "1 / 10/ 2023",
      "record_time": "2 : 27 : 35",
      "record_amount": "10",
      "record_balance": "9371",
      "recordId": 1,
      "id": 67
    },
    {
      "record_type": "Withdraw",
      "record_date": "1 / 10/ 2023",
      "record_time": "2 : 27 : 36",
      "record_amount": "10",
      "record_balance": "9371",
      "recordId": 1,
      "id": 68
    },
    {
      "record_type": "Withdraw",
      "record_date": "1 / 10/ 2023",
      "record_time": "2 : 27 : 56",
      "record_amount": "10",
      "record_balance": "9361",
      "recordId": 1,
      "id": 69
    },
    {
      "record_type": "Withdraw",
      "record_date": "1 / 10/ 2023",
      "record_time": "2 : 28 : 2",
      "record_amount": "10",
      "record_balance": "9361",
      "recordId": 1,
      "id": 70
    },
    {
      "record_type": "Withdraw",
      "record_date": "1 / 10/ 2023",
      "record_time": "2 : 28 : 9",
      "record_amount": "10",
      "record_balance": "9361",
      "recordId": 1,
      "id": 71
    },
    {
      "record_type": "Withdraw",
      "record_date": "1 / 10/ 2023",
      "record_time": "2 : 29 : 27",
      "record_amount": "800",
      "record_balance": "8561",
      "recordId": 1,
      "id": 72
    },
    {
      "record_type": "Withdraw",
      "record_date": "1 / 10/ 2023",
      "record_time": "2 : 29 : 31",
      "record_amount": "800",
      "record_balance": "8561",
      "recordId": 1,
      "id": 73
    },
    {
      "record_type": "Withdraw",
      "record_date": "1 / 10/ 2023",
      "record_time": "2 : 29 : 31",
      "record_amount": "800",
      "record_balance": "8561",
      "recordId": 1,
      "id": 74
    },
    {
      "record_type": "Withdraw",
      "record_date": "1 / 10/ 2023",
      "record_time": "2 : 29 : 31",
      "record_amount": "800",
      "record_balance": "8561",
      "recordId": 1,
      "id": 75
    },
    {
      "record_type": "Withdraw",
      "record_date": "1 / 10/ 2023",
      "record_time": "2 : 29 : 31",
      "record_amount": "800",
      "record_balance": "8561",
      "recordId": 1,
      "id": 76
    },
    {
      "record_type": "Withdraw",
      "record_date": "1 / 10/ 2023",
      "record_time": "2 : 34 : 29",
      "record_amount": "700",
      "record_balance": "7861",
      "recordId": 1,
      "id": 77
    },
    {
      "record_type": "Withdraw",
      "record_date": "1 / 10/ 2023",
      "record_time": "2 : 34 : 35",
      "record_amount": "700",
      "record_balance": "7861",
      "recordId": 1,
      "id": 78
    },
    {
      "record_type": "Withdraw",
      "record_date": "1 / 10/ 2023",
      "record_time": "2 : 35 : 15",
      "record_amount": "700",
      "record_balance": "7861",
      "recordId": 1,
      "id": 79
    },
    {
      "record_type": "Withdraw",
      "record_date": "1 / 10/ 2023",
      "record_time": "2 : 35 : 16",
      "record_amount": "700",
      "record_balance": "7861",
      "recordId": 1,
      "id": 80
    },
    {
      "record_type": "Withdraw",
      "record_date": "1 / 10/ 2023",
      "record_time": "2 : 42 : 22",
      "record_amount": "700",
      "record_balance": "7161",
      "recordId": 1,
      "id": 81
    },
    {
      "record_type": "Withdraw",
      "record_date": "1 / 10/ 2023",
      "record_time": "2 : 42 : 35",
      "record_amount": "700",
      "record_balance": "7161",
      "recordId": 1,
      "id": 82
    },
    {
      "record_type": "Withdraw",
      "record_date": "1 / 10/ 2023",
      "record_time": "2 : 44 : 56",
      "record_amount": "700",
      "record_balance": "7161",
      "recordId": 1,
      "id": 83
    },
    {
      "record_type": "Withdraw",
      "record_date": "1 / 10/ 2023",
      "record_time": "2 : 46 : 41",
      "record_amount": "700",
      "record_balance": "6461",
      "recordId": 1,
      "id": 84
    },
    {
      "record_type": "Withdraw",
      "record_date": "1 / 10/ 2023",
      "record_time": "2 : 47 : 35",
      "record_amount": "1000",
      "record_balance": "6161",
      "recordId": 1,
      "id": 85
    },
    {
      "record_type": "Withdraw",
      "record_date": "1 / 10/ 2023",
      "record_time": "2 : 47 : 54",
      "record_amount": "700",
      "record_balance": "6461",
      "recordId": 1,
      "id": 86
    },
    {
      "record_type": "Withdraw",
      "record_date": "1 / 10/ 2023",
      "record_time": "2 : 48 : 29",
      "record_amount": "700",
      "record_balance": "5761",
      "recordId": 1,
      "id": 87
    },
    {
      "record_type": "Withdraw",
      "record_date": "1 / 10/ 2023",
      "record_time": "2 : 48 : 55",
      "record_amount": "700",
      "record_balance": "5761",
      "recordId": 1,
      "id": 88
    },
    {
      "record_type": "Withdraw",
      "record_date": "1 / 10/ 2023",
      "record_time": "2 : 48 : 58",
      "record_amount": "500",
      "record_balance": "5261",
      "recordId": 1,
      "id": 89
    },
    {
      "record_type": "Withdraw",
      "record_date": "1 / 10/ 2023",
      "record_time": "14 : 7 : 4",
      "record_amount": "1000",
      "record_balance": "4261",
      "recordId": 1,
      "id": 90
    },
    {
      "record_type": "Deposit",
      "record_date": "1 / 10/ 2023",
      "record_time": "14 : 7 : 42",
      "record_amount": "23123123123123321312312312312312312312",
      "record_balance": "2.312312312312332e+37",
      "recordId": 1,
      "id": 91
    },
    {
      "record_type": "Withdraw",
      "record_date": "1 / 10/ 2023",
      "record_time": "15 : 3 : 38",
      "record_amount": "700",
      "record_balance": "101300",
      "recordId": 12,
      "id": 92
    },
    {
      "record_type": "Deposit",
      "record_date": "1 / 10/ 2023",
      "record_time": "15 : 10 : 48",
      "record_amount": "1555",
      "record_balance": "102855",
      "recordId": 12,
      "id": 93
    },
    {
      "record_type": "Deposit",
      "record_date": "1 / 10/ 2023",
      "record_time": "15 : 11 : 4",
      "record_amount": "20000",
      "record_balance": "122855",
      "recordId": 12,
      "id": 94
    },
    {
      "record_type": "Deposit",
      "record_date": "1 / 10/ 2023",
      "record_time": "15 : 11 : 12",
      "record_amount": "7878",
      "record_balance": "130733",
      "recordId": 12,
      "id": 95
    },
    {
      "record_type": "Withdraw",
      "record_date": "1 / 10/ 2023",
      "record_time": "15 : 12 : 24",
      "record_amount": "800",
      "record_balance": "129933",
      "recordId": 12,
      "id": 96
    },
    {
      "record_type": "Withdraw",
      "record_date": "1 / 10/ 2023",
      "record_time": "15 : 12 : 50",
      "record_amount": "1000",
      "record_balance": "128933",
      "recordId": 12,
      "id": 97
    }
  ]
}